filter_rrlyr/__init__.py
filter_rrlyr/filter.py
finkfilters-0.1.4.dist-info/LICENSE
finkfilters-0.1.4.dist-info/METADATA
finkfilters-0.1.4.dist-info/WHEEL
finkfilters-0.1.4.dist-info/top_level.txt
finkfilters-0.1.4.dist-info/RECORD
