Metadata-Version: 2.1
Name: finkfilters
Version: 0.1.4
Summary: User-defined filters for the Fink broker.
Home-page: https://fink-broker.readthedocs.io/en/latest/
Author: JulienPeloton
Author-email: peloton@lal.in2p3.fr
License: UNKNOWN
Project-URL: Documentation, https://fink-broker.readthedocs.io/en/latest/
Project-URL: Source, https://github.com/astrolabsoftware/finkfilters
Platform: UNKNOWN
Classifier: Programming Language :: Python :: 3.6
Classifier: Programming Language :: Python :: 3.7
Classifier: License :: OSI Approved :: Apache Software License
Classifier: Operating System :: Unix
Classifier: Development Status :: 4 - Beta
Classifier: Intended Audience :: Science/Research
